dh_poetry/__init__.py
dh_poetry/command_line.py
dh_poetry_cypherpunkdev-0.2.5.dist-info/METADATA
dh_poetry_cypherpunkdev-0.2.5.dist-info/WHEEL
dh_poetry_cypherpunkdev-0.2.5.dist-info/entry_points.txt
dh_poetry_cypherpunkdev-0.2.5.dist-info/top_level.txt
dh_poetry_cypherpunkdev-0.2.5.dist-info/RECORD
