Metadata-Version: 2.1
Name: dh-poetry-cypherpunkdev
Version: 0.2.5
Summary: Shim between dh-virtualenv and poetry
Home-page: https://github.com/CypherpunkDev/dh-poetry
Author: CypherpunkDev
Author-email: maikelwever@gmail.com
License: MIT
